Workbook

Sheet Dashboard
U2: ='Audit Report'!C8 -> 0
C3: Category | D3: ='FD Calculator'!C3 -> General | F3: Lumpsum | I3: SIP
C4: FD Amount | D4: ='FD Calculator'!C4 -> 1000000 | F4: Investment | G4: ='Investment Calculator'!C4 -> 200000 | I4: Monthly Payment | J4: ='Investment Calculator'!C6 -> 15000
C5: Interest | D5: ='FD Calculator'!C5 -> 917888.68 | F5: Future Amount | G5: ='Investment Calculator'!F5 -> 363339.34 | I5: Total Investment | J5: =J4*'Investment Calculator'!C8*'Investment Calculator'!F4 -> 900000
C6: Future Amount | D6: ='FD Calculator'!C9 -> 1917888.7 | F6: Interest Rate | G6: ='Investment Calculator'!C5 -> 0.12 | I6: Future Amount | J6: ='Investment Calculator'!F6 -> 1237295.5
C7: Interest Rate | D7: ='FD Calculator'!C7 -> 0.0675 | I7: Interest Rate | J7: ='Investment Calculator'!C7 -> 0.12
G9: Total
G10: Total Investment | I10: =(G4)+(J4*'Investment Calculator'!C8*'Investment Calculator'!F4) -> 1100000
G11: Future Value | I11: =G5+J6 -> 1600634.8
G12: After Adjustment | I12: ='Investment Calculator'!F9 -> 1474897.7

Sheet FD Calculator
B3: Category | C3: General | F3: Duration
B4: Investment | C4: 1000000 | F4: Year | G4: Months | H4: Days
B5: Interest Amount | C5: =IFERROR((C9-C4),"") -> 917888.68 | F5: 9 | G5: 8 | H5: 3
B6: Tenure (years) | C6: =(F5) + (G5/12) + (H5/365) -> 9.6748858 | D6: {=_xlfn.IFS(C6<7/365, "Less than 7 days", AND(C6>=7/365, C6<3/12), "7 days – 3 months", AND(C6>=3/12, C6<6/12), "3 months – 6 months",AND(C6>=6/12, C6<1), "6 months – 1 year",AND(C6>=1, C6<3), "1 year – 3 years",AND(C6>=3, C6<5), "3 years – 5 years", AND(C6>=5, C6<=10), "5 years – 10 years",TRUE, "Over 10 years")} -> 5 years – 10 years
B7: Interest Rate | C7: =IFERROR(IF(C3="General",VLOOKUP(D6,'(Reference Table)'!C4:E9,2,0),VLOOKUP(D6,'(Reference Table)'!C3:E9,3,0)),"") -> 0.0675
B8: Frequency | C8: =VLOOKUP(D8,'(Reference Table)'!G3:I6,2,0) -> 12 | D8: Monthly
B9: Maturity Amount | C9: =IFERROR(ABS(FV(C7/C8,C6*C8,,C4)),"Please Renew") -> 1917888.7

Sheet Investment Calculator
B3: Input | E3: Output
B4: Principal Investment | C4: 200000 | E4: Periods per Year | F4: =IFERROR(VLOOKUP(C9,'(Reference Table)'!G3:I6,2,FALSE),"") -> 12
B5: Annual Return(Lumpsum) | C5: =D5/100 -> 0.12 | D5: 12 | E5: Lumpsum Future Value | F5: =ABS(FV(C5/F4,C8*F4,,C4)) -> 363339.34
B6: Monthly SIP Amount | C6: 15000 | E6: SIP Future Value | F6: =ABS(FV(C7/F4,C8*F4,C6,,1)) -> 1237295.5
B7: Annual Return(SIP) | C7: =D7/100 -> 0.12 | D7: 12 | E7: Total Future Value | F7: =F5 + F6 -> 1600634.8
B8: Investment Duration (Years) | C8: 5 | E8: Adjust for Expense Ratio | F8: =F7 * (1 - (C10)) -> 1568622.1
B9: Compounding Frequency | C9: Monthly | E9: Adjust for Tax | F9: =F8-((F8-(C4+(C6*C8*F4)))*C11) -> 1474897.7
B10: Expense Ratio | C10: 0.02
B11: Tax Rate on Gains | C11: 0.2

Sheet SIP Schedule
C2: SIP Schedule
C4: Period | D4: SIP Deposit | E4: Interest Earned | F4: Total Value
C5: 1 | D5: =IF(C5<='Investment Calculator'!$C$8*'Investment Calculator'!$F$4,'Investment Calculator'!$C$6,"") -> 15000 | E5: =IFERROR(D5*'Investment Calculator'!C7/'Investment Calculator'!F4,"") -> 150 | F5: =IFERROR(ABS(FV('Investment Calculator'!$C$7/'Investment Calculator'!$F$4,'SIP Schedule'!C5,'SIP Schedule'!D5,,1)),"") -> 15150
C6: =IF(C5<'Investment Calculator'!$C$8*'Investment Calculator'!$F$4,'SIP Schedule'!C5+1,"") -> 2 | D6: =IF(C6<='Investment Calculator'!$C$8*'Investment Calculator'!$F$4,'Investment Calculator'!$C$6,"") -> 15000 | E6: =IFERROR((F5+D6)*'Investment Calculator'!$C$7/'Investment Calculator'!$F$4,"") -> 301.5 | F6: =IFERROR(ABS(FV('Investment Calculator'!$C$7/'Investment Calculator'!$F$4,'SIP Schedule'!C6,'SIP Schedule'!D6,,1)),"") -> 30451.5
C7: =IF(C6<'Investment Calculator'!$C$8*'Investment Calculator'!$F$4,'SIP Schedule'!C6+1,"") -> 3 | D7: =IF(C7<='Investment Calculator'!$C$8*'Investment Calculator'!$F$4,'Investment Calculator'!$C$6,"") -> 15000 | E7: =IFERROR((F6+D7)*'Investment Calculator'!$C$7/'Investment Calculator'!$F$4,"") -> 454.515 | F7: =IFERROR(ABS(FV('Investment Calculator'!$C$7/'Investment Calculator'!$F$4,'SIP Schedule'!C7,'SIP Schedule'!D7,,1)),"") -> 45906.015
C8: =IF(C7<'Investment Calculator'!$C$8*'Investment Calculator'!$F$4,'SIP Schedule'!C7+1,"") -> 4 | D8: =IF(C8<='Investment Calculator'!$C$8*'Investment Calculator'!$F$4,'Investment Calculator'!$C$6,"") -> 15000 | E8: =IFERROR((F7+D8)*'Investment Calculator'!$C$7/'Investment Calculator'!$F$4,"") -> 609.06015 | F8: =IFERROR(ABS(FV('Investment Calculator'!$C$7/'Investment Calculator'!$F$4,'SIP Schedule'!C8,'SIP Schedule'!D8,,1)),"") -> 61515.075
C9: =IF(C8<'Investment Calculator'!$C$8*'Investment Calculator'!$F$4,'SIP Schedule'!C8+1,"") -> 5 | D9: =IF(C9<='Investment Calculator'!$C$8*'Investment Calculator'!$F$4,'Investment Calculator'!$C$6,"") -> 15000 | E9: =IFERROR((F8+D9)*'Investment Calculator'!$C$7/'Investment Calculator'!$F$4,"") -> 765.15075 | F9: =IFERROR(ABS(FV('Investment Calculator'!$C$7/'Investment Calculator'!$F$4,'SIP Schedule'!C9,'SIP Schedule'!D9,,1)),"") -> 77280.226
C10: =IF(C9<'Investment Calculator'!$C$8*'Investment Calculator'!$F$4,'SIP Schedule'!C9+1,"") -> 6 | D10: =IF(C10<='Investment Calculator'!$C$8*'Investment Calculator'!$F$4,'Investment Calculator'!$C$6,"") -> 15000 | E10: =IFERROR((F9+D10)*'Investment Calculator'!$C$7/'Investment Calculator'!$F$4,"") -> 922.80226 | F10: =IFERROR(ABS(FV('Investment Calculator'!$C$7/'Investment Calculator'!$F$4,'SIP Schedule'!C10,'SIP Schedule'!D10,,1)),"") -> 93203.028
C11: =IF(C10<'Investment Calculator'!$C$8*'Investment Calculator'!$F$4,'SIP Schedule'!C10+1,"") -> 7 | D11: =IF(C11<='Investment Calculator'!$C$8*'Investment Calculator'!$F$4,'Investment Calculator'!$C$6,"") -> 15000 | E11: =IFERROR((F10+D11)*'Investment Calculator'!$C$7/'Investment Calculator'!$F$4,"") -> 1082.0303 | F11: =IFERROR(ABS(FV('Investment Calculator'!$C$7/'Investment Calculator'!$F$4,'SIP Schedule'!C11,'SIP Schedule'!D11,,1)),"") -> 109285.06
C12: =IF(C11<'Investment Calculator'!$C$8*'Investment Calculator'!$F$4,'SIP Schedule'!C11+1,"") -> 8 | D12: =IF(C12<='Investment Calculator'!$C$8*'Investment Calculator'!$F$4,'Investment Calculator'!$C$6,"") -> 15000 | E12: =IFERROR((F11+D12)*'Investment Calculator'!$C$7/'Investment Calculator'!$F$4,"") -> 1242.8506 | F12: =IFERROR(ABS(FV('Investment Calculator'!$C$7/'Investment Calculator'!$F$4,'SIP Schedule'!C12,'SIP Schedule'!D12,,1)),"") -> 125527.91
C13: =IF(C12<'Investment Calculator'!$C$8*'Investment Calculator'!$F$4,'SIP Schedule'!C12+1,"") -> 9 | D13: =IF(C13<='Investment Calculator'!$C$8*'Investment Calculator'!$F$4,'Investment Calculator'!$C$6,"") -> 15000 | E13: =IFERROR((F12+D13)*'Investment Calculator'!$C$7/'Investment Calculator'!$F$4,"") -> 1405.2791 | F13: =IFERROR(ABS(FV('Investment Calculator'!$C$7/'Investment Calculator'!$F$4,'SIP Schedule'!C13,'SIP Schedule'!D13,,1)),"") -> 141933.19
C14: =IF(C13<'Investment Calculator'!$C$8*'Investment Calculator'!$F$4,'SIP Schedule'!C13+1,"") -> 10 | D14: =IF(C14<='Investment Calculator'!$C$8*'Investment Calculator'!$F$4,'Investment Calculator'!$C$6,"") -> 15000 | E14: =IFERROR((F13+D14)*'Investment Calculator'!$C$7/'Investment Calculator'!$F$4,"") -> 1569.3319 | F14: =IFERROR(ABS(FV('Investment Calculator'!$C$7/'Investment Calculator'!$F$4,'SIP Schedule'!C14,'SIP Schedule'!D14,,1)),"") -> 158502.52
C15: =IF(C14<'Investment Calculator'!$C$8*'Investment Calculator'!$F$4,'SIP Schedule'!C14+1,"") -> 11 | D15: =IF(C15<='Investment Calculator'!$C$8*'Investment Calculator'!$F$4,'Investment Calculator'!$C$6,"") -> 15000 | E15: =IFERROR((F14+D15)*'Investment Calculator'!$C$7/'Investment Calculator'!$F$4,"") -> 1735.0252 | F15: =IFERROR(ABS(FV('Investment Calculator'!$C$7/'Investment Calculator'!$F$4,'SIP Schedule'!C15,'SIP Schedule'!D15,,1)),"") -> 175237.55
C16: =IF(C15<'Investment Calculator'!$C$8*'Investment Calculator'!$F$4,'SIP Schedule'!C15+1,"") -> 12 | D16: =IF(C16<='Investment Calculator'!$C$8*'Investment Calculator'!$F$4,'Investment Calculator'!$C$6,"") -> 15000 | E16: =IFERROR((F15+D16)*'Investment Calculator'!$C$7/'Investment Calculator'!$F$4,"") -> 1902.3755 | F16: =IFERROR(ABS(FV('Investment Calculator'!$C$7/'Investment Calculator'!$F$4,'SIP Schedule'!C16,'SIP Schedule'!D16,,1)),"") -> 192139.92
C17: =IF(C16<'Investment Calculator'!$C$8*'Investment Calculator'!$F$4,'SIP Schedule'!C16+1,"") -> 13 | D17: =IF(C17<='Investment Calculator'!$C$8*'Investment Calculator'!$F$4,'Investment Calculator'!$C$6,"") -> 15000 | E17: =IFERROR((F16+D17)*'Investment Calculator'!$C$7/'Investment Calculator'!$F$4,"") -> 2071.3992 | F17: =IFERROR(ABS(FV('Investment Calculator'!$C$7/'Investment Calculator'!$F$4,'SIP Schedule'!C17,'SIP Schedule'!D17,,1)),"") -> 209211.32
... C4526: =IF(C4525<'Investment Calculator'!$C$8*'Investment Calculator'!$F$4,'SIP Schedule'!C4525+1,"") | D4526: =IF(C4526<='Investment Calculator'!$C$8*'Investment Calculator'!$F$4,'Investment Calculator'!$C$6,"") | E4526: =IFERROR((F4525+D4526)*'Investment Calculator'!$C$7/'Investment Calculator'!$F$4,"") | F4526: =IFERROR(ABS(FV('Investment Calculator'!$C$7/'Investment Calculator'!$F$4,'SIP Schedule'!C4526,'SIP Schedule'!D4526,,1)),"")

Sheet Audit Report
B3: Sheet | C3: Errors
B4: Dashboard | C4: {=SUM(IF(ISERROR(Dashboard!B2:T24),1))} -> 0
B5: FD Calculator | C5: {=SUM(IF(ISERROR('FD Calculator'!B3:K9),1))} -> 0
B6: Investment Calculator | C6: {=SUM(IF(ISERROR('Investment Calculator'!B3:I12),1))} -> 0
B7: SIP Schedule | C7: {=SUM(IF(ISERROR('SIP Schedule'!C2:F4526),1))} -> 0
B8: Total | C8: =SUM(C4:C7) -> 0

Sheet Information Sheet

Sheet (Reference Table)
C3: Tenure Range | D3: Average Interest Rate (General) | E3: Average Interest Rate (Senior Citizens) | G3: Annual | H3: 1 | I3: 12
C4: 7 days – 3 months | D4: 0.0425 | E4: 0.0475 | G4: Semi-Annual | H4: 2 | I4: 6
C5: 3 months – 6 months | D5: 0.055 | E5: 0.06 | G5: Quarterly | H5: 4 | I5: 3
C6: 6 months – 1 year | D6: 0.065 | E6: 0.07 | G6: Monthly | H6: 12 | I6: 1
C7: 1 year – 3 years | D7: 0.07 | E7: 0.075
C8: 3 years – 5 years | D8: 0.0725 | E8: 0.0775
C9: 5 years – 10 years | D9: 0.0675 | E9: 0.0725
